utithon/__init__.py
utithon/logging/__init__.py
utithon/logging/json_logger.py
utithon-0.0.1.dist-info/METADATA
utithon-0.0.1.dist-info/WHEEL
utithon-0.0.1.dist-info/licenses/LICENSE
utithon-0.0.1.dist-info/RECORD
